markus_autotest_helpers_sql/__init__.py
markus_autotest_helpers_sql-0.1.0.dist-info/WHEEL
markus_autotest_helpers_sql-0.1.0.dist-info/METADATA
markus_autotest_helpers_sql-0.1.0.dist-info/RECORD
